setup.py
ijkl/__init__.py
ijkl/cli.py
ijkl/parser.py
ijkl.egg-info/PKG-INFO
ijkl.egg-info/SOURCES.txt
ijkl.egg-info/dependency_links.txt
ijkl.egg-info/entry_points.txt
ijkl.egg-info/top_level.txt