Metadata-Version: 1.1
Name: ijkl
Version: 0.1.0
Summary: Preprocessor for i3 Configuration
Home-page: http://github.com/ankitrgadiya/ijkl
Author: Ankit R Gadiya
Author-email: git@argp.in
License: BSD 3-Clause
Platform: UNKNOWN
Classifier: Development Status :: 3 - Alpha
Classifier: Environment :: Console
Classifier: Intended Audience :: End Users/Desktop
Classifier: License :: OSI Approved :: BSD License
Classifier: Programming Language :: Python :: 3
Classifier: Topic :: Utilities
